html_minifier/minify.py
html_minifier/test.py
html_minifier/__init__.py
html_minifier-0.0.4.dist-info/DESCRIPTION.rst
html_minifier-0.0.4.dist-info/METADATA
html_minifier-0.0.4.dist-info/metadata.json
html_minifier-0.0.4.dist-info/RECORD
html_minifier-0.0.4.dist-info/top_level.txt
html_minifier-0.0.4.dist-info/WHEEL
