Metadata-Version: 2.0
Name: html-minifier
Version: 0.0.4
Summary: a module for minify html
Home-page: https://github.com/Kaumer/html-minifier
Author: Leonardo orozco
Author-email: UNKNOWN
License: UNKNOWN
Keywords: html,minifier
Platform: UNKNOWN
Classifier: Development Status :: 4 - Beta
Classifier: Environment :: Web Environment
Classifier: Intended Audience :: Developers
Classifier: License :: OSI Approved :: MIT License
Classifier: Operating System :: OS Independent
Classifier: Programming Language :: Python :: 2.7
Classifier: Programming Language :: Python :: 3.4
Classifier: Topic :: Utilities
